rtl/mux2to1.sv
module mux2to1 (
    input logic a,
    input logic b,
    input logic sel,
    output logic y
);
    assign y = sel ? b : a;
endmodule

tb/tb_mux2to1.sv
`timescale 1ns/1ps

module tb_mux2to1;

    logic a, b, sel, y;

    mux2to1 dut(
        .a(a),
        .b(b),
        .sel(sel),
        .y(y)
    );

    initial begin
        $dumpfile("sim/mux2to1.vcd");
        $dumpvars(0, tb_mux2to1);
    end

    initial begin
        a = 0; b = 0; sel = 0; #10;
        $display("a=%b b=%b sel=%b y=%b | expect 0", a, b, sel, y);

        a = 0; b = 1; sel = 0; #10;
        $display("a=%b b=%b sel=%b y=%b | expect 0", a, b, sel, y);

        a = 1; b = 0; sel = 0; #10;
        $display("a=%b b=%b sel=%b y=%b | expect 1", a, b, sel, y);

        a = 1; b = 1; sel = 0; #10;
        $display("a=%b b=%b sel=%b y=%b | expect 1", a, b, sel, y);

        a = 0; b = 0; sel = 1; #10;
        $display("a=%b b=%b sel=%b y=%b | expect 0", a, b, sel, y);

        a = 0; b = 1; sel = 1; #10;
        $display("a=%b b=%b sel=%b y=%b | expect 1", a, b, sel, y);

        a = 1; b = 0; sel = 1; #10;
        $display("a=%b b=%b sel=%b y=%b | expect 0", a, b, sel, y);

        a = 1; b = 1; sel = 1; #10;
        $display("a=%b b=%b sel=%b y=%b | expect 1", a, b, sel, y);

        $finish;
    end
endmodule

sim/mux2to1.vcd
$date
	Fri Jun  5 18:36:53 2026
$end
$version
	Icarus Verilog
$end
$timescale
	1ps
$end
$scope module tb_mux2to1 $end
$var wire 1 ! y $end
$var reg 1 " a $end
$var reg 1 # b $end
$var reg 1 $ sel $end
$scope module dut $end
$var wire 1 " a $end
$var wire 1 # b $end
$var wire 1 $ sel $end
$var wire 1 ! y $end
$upscope $end
$upscope $end
$enddefinitions $end
$comment Show the parameter values. $end
$dumpall
$end
#0
$dumpvars
0$
0#
0"
0!
$end
#10000
1#
#20000
1!
0#
1"
#30000
1#
#40000
0!
1$
0#
0"
#50000
1!
1#
#60000
0!
0#
1"
#70000
1!
1#
